atlas_object_partitioning/__about__.py
atlas_object_partitioning/__init__.py
atlas_object_partitioning/histograms.py
atlas_object_partitioning/local_mode.py
atlas_object_partitioning/partition.py
atlas_object_partitioning/scan_ds.py
atlas_object_partitioning-1.2.0.dist-info/METADATA
atlas_object_partitioning-1.2.0.dist-info/WHEEL
atlas_object_partitioning-1.2.0.dist-info/entry_points.txt
atlas_object_partitioning-1.2.0.dist-info/top_level.txt
atlas_object_partitioning-1.2.0.dist-info/RECORD
