Metadata-Version: 2.4
Name: atlas-object-partitioning
Version: 1.2.0
Summary: Object partitioning package.
Author-email: Gordon Watts <gwatts@uw.edu>
Requires-Python: >=3.10
Requires-Dist: typer
Requires-Dist: func_adl_servicex_xaodr25
Requires-Dist: servicex_analysis_utils
Requires-Dist: jinja2
Requires-Dist: pyarrow
Requires-Dist: hist
Provides-Extra: test
Requires-Dist: pytest; extra == "test"
Requires-Dist: pytest-cov; extra == "test"
Requires-Dist: flake8; extra == "test"
Requires-Dist: black; extra == "test"
Requires-Dist: coverage; extra == "test"
Provides-Extra: local
Requires-Dist: servicex-local; extra == "local"
Requires-Dist: func_adl_xAOD; extra == "local"
